__init__.py
django_clite/__init__.py
django_clite/cli.py
django_clite/constants.py
django_clite/utils.py
django_clite/commands/__init__.py
django_clite/commands/callbacks.py
django_clite/commands/command_defaults.py
django_clite/commands/destroy/__init__.py
django_clite/commands/destroy/admin.py
django_clite/commands/destroy/dockerfile.py
django_clite/commands/destroy/fixtures.py
django_clite/commands/destroy/forms.py
django_clite/commands/destroy/main.py
django_clite/commands/destroy/management.py
django_clite/commands/destroy/managers.py
django_clite/commands/destroy/models.py
django_clite/commands/destroy/serializers.py
django_clite/commands/destroy/signals.py
django_clite/commands/destroy/tags.py
django_clite/commands/destroy/template.py
django_clite/commands/destroy/tests.py
django_clite/commands/destroy/validators.py
django_clite/commands/destroy/views.py
django_clite/commands/destroy/viewsets.py
django_clite/commands/generate/__init__.py
django_clite/commands/generate/admin.py
django_clite/commands/generate/dockerfile.py
django_clite/commands/generate/fixtures.py
django_clite/commands/generate/forms.py
django_clite/commands/generate/main.py
django_clite/commands/generate/management.py
django_clite/commands/generate/managers.py
django_clite/commands/generate/models.py
django_clite/commands/generate/serializers.py
django_clite/commands/generate/signals.py
django_clite/commands/generate/tags.py
django_clite/commands/generate/template.py
django_clite/commands/generate/tests.py
django_clite/commands/generate/validators.py
django_clite/commands/generate/views.py
django_clite/commands/generate/viewsets.py
django_clite/commands/new/__init__.py
django_clite/commands/new/app.py
django_clite/commands/new/main.py
django_clite/commands/new/project.py
django_clite/commands/new/defaults/__init__.py
django_clite/commands/new/defaults/app.py
django_clite/commands/new/defaults/project.py
django_clite/core/__init__.py
django_clite/core/logger.py
django_clite-0.19.7.dist-info/LICENSE
django_clite-0.19.7.dist-info/METADATA
django_clite-0.19.7.dist-info/WHEEL
django_clite-0.19.7.dist-info/entry_points.txt
django_clite-0.19.7.dist-info/top_level.txt
django_clite-0.19.7.dist-info/RECORD
